Booth Multiplier/main.v

module booth_multiplier(
    output [15:0] ans,
    input [7:0] m,r,
    input clk,rst,start,
    output reg ready);

    reg signed[16:0] P_temp;  
    wire signed[16:0] P;   
    reg signed[16:0] A,S;   
    reg carry;   
    reg [2:0] count;
    reg state;

    assign P=P_temp>>>1;
    // assign ready=(state==idle);
    assign ans = P[16:1]; 

    parameter idle = 2'b00,busy = 2'b01;

    always@(posedge clk, negedge rst)  
        if (!rst) begin 
            A <= 16'b0;
            S <= 16'b0;
            P_temp <= 16'b0;
            state <= idle;
            ready<=1'b1;
        end 
        else begin
            case(state)
            idle: begin
                if(start)begin
                    A <= {m,9'b000000000};    
                    S <= {~m+1'b1,9'b000000000};  
                    P_temp <= {7'b0000000,r,2'b0};
                    count<=3'd0;
                    state<=busy;
                    ready<=1'b0;
                end
                else begin
                    ready<=1'b1;
                end
            end
            busy: begin
                case(P[1:0])
                    2'b01 : {carry,P_temp} <= (P+A);
                    2'b10 : {carry,P_temp} <= (P+S);
                    2'b00 : P_temp <= P;
                    2'b11 : P_temp <= P;
                endcase
                if(count!=3'd7)begin
                    count<=count+1;
                end
                else begin
                    count<=3'b0;
                    state<=idle;
                end
            end
            default: state<=idle;
            endcase
   end
endmodule

Booth Multiplier/t_main.v
module t_booth_multiplier; // module creation 2033
  wire[15:0] t_ans;  //wire for outputs 2033
  reg [7:0] t_m,t_r;   // reg for inputs 2033 
  reg t_clk,t_rst,t_shift_control;  // reg for clk and reset 2033
  reg t_start;
  wire ready;
  booth_multiplier m1(t_ans,t_m,t_r,t_clk,t_rst,t_start,t_ready);  // module instantion 2033
  initial begin  // applying inputs 2033
    t_clk=1'b0;   // 2033
    t_start=1'b0;
    t_shift_control=1'b0;  // 2033
    t_m=8'b0100001;  //33 input 2033
    t_r=8'b0010100;  //20 input 2033
    // reseting so module loads values 2033
    t_rst=1'b0; // 2033
    #5 t_rst=1'b1;  // 2033
    repeat(50) // 2033
    #5 t_clk = ~t_clk;  // 2033
  end // 2033
  initial begin   // shift control high for 8 cycles changes at -ve edge 2033
    #15 t_shift_control = 1'b1;  // 2033
    t_start=1'b1;
    #20 t_start=1'b0;
    #80 t_shift_control = 1'b0;   // 2033
  end  //2033
  initial begin
        //$monitor("a=%b,b=%b,sel=%b,out=%b",ta,tb,tsel,tout);
        $dumpfile("booth_multiplier.vcd"); //Specify the file where all the variables will be dumped.
        $dumpvars;
    end
endmodule //2033

Booth Multiplier/booth_multiplier.vcd
$date
	Sat Nov 06 16:21:18 2021
$end
$version
	Icarus Verilog
$end
$timescale
	1s
$end
$scope module t_booth_multiplier $end
$var wire 1 ! t_ready $end
$var wire 16 " t_ans [15:0] $end
$var reg 1 # t_clk $end
$var reg 8 $ t_m [7:0] $end
$var reg 8 % t_r [7:0] $end
$var reg 1 & t_rst $end
$var reg 1 ' t_shift_control $end
$var reg 1 ( t_start $end
$scope module m1 $end
$var wire 1 # clk $end
$var wire 8 ) m [7:0] $end
$var wire 8 * r [7:0] $end
$var wire 1 & rst $end
$var wire 1 ( start $end
$var wire 1 ! ready $end
$var wire 16 + ans [15:0] $end
$var wire 17 , P [16:0] $end
$var reg 17 - A [16:0] $end
$var reg 17 . P_temp [16:0] $end
$var reg 17 / S [16:0] $end
$var reg 1 0 carry $end
$var reg 3 1 count [2:0] $end
$var reg 1 2 state $end
$upscope $end
$upscope $end
$enddefinitions $end
#0
$dumpvars
02
bx 1
x0
b0 /
b0 .
b0 -
b0 ,
b0 +
b10100 *
b100001 )
0(
0'
0&
b10100 %
b100001 $
0#
b0 "
1!
$end
#5
1&
#10
1#
#15
0#
1(
1'
#20
b10100 "
b10100 +
b101000 ,
0!
12
b0 1
b1010000 .
b11011111000000000 /
b100001000000000 -
1#
#25
0#
#30
b1010 "
b1010 +
b10100 ,
b1 1
b101000 .
1#
#35
0#
0(
#40
b101 "
b101 +
b1010 ,
b10 1
b10100 .
1#
#45
0#
#50
b1110111110000010 "
b1110111110000010 +
b11101111100000101 ,
b11 1
10
b11011111000001010 .
1#
#55
0#
#60
b100001000001 "
b100001000001 +
b1000010000010 ,
b100 1
00
b10000100000101 .
1#
#65
0#
#70
b1111001110100000 "
b1111001110100000 +
b11110011101000001 ,
b101 1
10
b11100111010000010 .
1#
#75
0#
#80
b101001010000 "
b101001010000 +
b1010010100000 ,
b110 1
00
b10100101000001 .
1#
#85
0#
#90
b10100101000 "
b10100101000 +
b101001010000 ,
b111 1
b1010010100000 .
1#
#95
0#
#100
b1010010100 "
b1010010100 +
b10100101000 ,
1!
02
b0 1
b101001010000 .
1#
#105
0#
#110
1#
#115
0#
0'
