Booth Multiplier/main.v

module booth_multiplier(
    output [15:0] ans,
    input [7:0] m1,r,
    input clk,rst,start,
    output reg ready
    );

    wire [8:0] m;
    
    reg [8:0] P_tempH,P_tempL;  
    wire signed[17:0] P;   
    wire signed[8:0] A,S;   
    reg carry;   
    reg [2:0] count;
    reg state;

    assign P={P_tempH[8],P_tempH,P_tempL[8:1]};
    // assign ready=(state==idle);
    assign ans = P[16:1]; 
    assign m = {m1[7],m1[7],m1[6:0]};
    parameter idle = 2'b00,busy = 2'b01;
    assign A = m;    
    assign S = ~m+1'b1;  

    always@(posedge clk, negedge rst)  
        if (!rst) begin
            P_tempH <= 9'b0;
            P_tempL <= 9'b0;
            state <= idle;
            ready<=1'b1;
        end 
        else begin
            case(state)
            idle: begin
                if(start) begin
                    P_tempH <= {8'b0000000,r[7]};
                    P_tempL <= {r[6:0],2'b0};
                    count<=3'd0;
                    state<=busy;
                    ready<=1'b0;
                end
                else begin
                    ready<=1'b1;
                end
            end
            busy: begin
                case(P[1:0])
                    2'b01 : {carry,P_tempH} <= P[17:9]+A;
                    2'b10 : {carry,P_tempH} <= P[17:9]+S;
                    2'b00 : P_tempH <= P[17:9];
                    2'b11 : P_tempH <= P[17:9];
                endcase
                P_tempL<=P[8:0];
                if(count!=3'd7)begin
                    count<=count+1;
                end
                else begin
                    count<=3'b0;
                    state<=idle;
                end
            end
            default: state<=idle;
            endcase
        end
endmodule

Booth Multiplier/t_main2.v
`include "main.v"

module t_booth_multiplier; 
  wire signed [15:0] t_ans;  
  reg  signed [7:0] t_m,t_r;   
  reg t_clk,t_rst;  
  reg t_start;
  wire ready;
  integer i,j,error;
  booth_multiplier m1(t_ans,t_m,t_r,t_clk,t_rst,t_start,t_ready); 
  initial begin 
    t_clk=1'b0;   
    t_start=1'b0; 
    t_m=8'b0100001;  
    t_r=8'b0010100;  
    t_rst=1'b0; 
    #5 t_rst=1'b1; 
    // t_m <= 8'b10000000;
    // t_r <= 8'b00000001;
    #1;
    // t_start=1'b1;
    // #20 t_start=1'b0;
    // #100;
    // $display("%d %d %d",t_ans,t_m,t_r);
    // #10 $finish;
    // error = error + 1;
  end
  always #5 t_clk=~t_clk;
  initial begin
        error = 0;
        for(i = 0;i <= 255;i = i+1)
            for(j = 0;j <= 255;j = j+1) begin
                t_m <= i;
                t_r <= j;
                #1;
                t_start=1'b1;
                #20 t_start=1'b0;
                #100;
                if (t_ans != t_m*t_r) begin
                    // $display("%d %d %d",t_ans,t_m,t_r);
                    // #10 $finish;
                    error = error + 1;
                end
                    
            end
        $display("%d",error);
        #10 $finish;
    end
    // initial begin
    //     $dumpfile("booth_multiplier3.vcd");
    //     $dumpvars;
    // end
endmodule

Booth Multiplier/booth_multiplier3.vcd
$date
	Sun Dec 12 20:49:43 2021
$end
$version
	Icarus Verilog
$end
$timescale
	1s
$end
$scope module t_booth_multiplier $end
$var wire 1 ! t_ready $end
$var wire 16 " t_ans [15:0] $end
$var reg 1 # t_clk $end
$var reg 8 $ t_m [7:0] $end
$var reg 8 % t_r [7:0] $end
$var reg 1 & t_rst $end
$var reg 1 ' t_start $end
$var integer 32 ( error [31:0] $end
$var integer 32 ) i [31:0] $end
$var integer 32 * j [31:0] $end
$scope module m1 $end
$var wire 9 + A [8:0] $end
$var wire 1 # clk $end
$var wire 8 , m1 [7:0] $end
$var wire 8 - r [7:0] $end
$var wire 1 & rst $end
$var wire 1 ' start $end
$var wire 9 . m [8:0] $end
$var wire 16 / ans [15:0] $end
$var wire 9 0 S [8:0] $end
$var wire 18 1 P [17:0] $end
$var reg 9 2 P_tempH [8:0] $end
$var reg 9 3 P_tempL [8:0] $end
$var reg 1 4 carry $end
$var reg 3 5 count [2:0] $end
$var reg 1 ! ready $end
$var reg 1 6 state $end
$upscope $end
$upscope $end
$enddefinitions $end
#0
$dumpvars
06
bx 5
x4
b0 3
b0 2
b0 1
b0 0
b0 /
b0 .
b0 -
b0 ,
b0 +
b0 *
b0 )
b0 (
0'
0&
b0 %
b0 $
0#
b0 "
1!
$end
#1
1'
#5
0!
16
b0 5
1#
1&
#10
0#
#15
b1 5
1#
#20
0#
#21
0'
#25
b10 5
1#
#30
0#
#35
b11 5
1#
#40
0#
#45
b100 5
1#
#50
0#
#55
b101 5
1#
#60
0#
#65
b110 5
1#
#70
0#
#75
b111 5
1#
#80
0#
#85
06
b0 5
1#
#90
0#
#95
1!
1#
#100
0#
#105
1#
#110
0#
#115
1#
#120
0#
#121
b1 %
b1 -
b1 *
#122
1'
#125
b1 1
0!
16
b10 3
1#
#130
0#
#135
b0 1
b1 5
b1 3
04
1#
#140
0#
#142
0'
#145
b10 5
b0 3
1#
#150
0#
#155
b11 5
1#
#160
0#
#165
b100 5
1#
#170
0#
#175
b101 5
1#
#180
0#
#185
b110 5
1#
#190
0#
#195
b111 5
1#
#200
0#
#205
06
b0 5
1#
#210
0#
#215
1!
1#
#220
0#
#225
1#
#230
0#
#235
1#
#240
0#
#242
b10 %
b10 -
b10 *
#243
1'
#245
b1 "
b1 /
b10 1
0!
16
b100 3
1#
#250
0#
#255
b0 "
b0 /
b1 1
b1 5
b10 3
1#
#260
0#
#263
0'
#265
b0 1
b10 5
b1 3
1#
#270
0#
#275
b11 5
b0 3
1#
#280
0#
#285
b100 5
1#
#290
0#
#295
b101 5
1#
#300
0#
#305
b110 5
1#
#310
0#
#315
b111 5
1#
#320
0#
#325
06
b0 5
1#
#330
0#
#335
1!
1#
#340
0#
#345
1#
#350
0#
#355
1#
#360
0#
#363
b11 %
b11 -
b11 *
#364
1'
#365
b1 "
b1 /
b11 1
0!
16
b110 3
1#
#370
0#
#375
b0 "
b0 /
b1 1
b1 5
b11 3
1#
#380
0#
#384
0'
#385
b0 1
b10 5
b1 3
1#
#390
0#
#395
b11 5
b0 3
1#
#400
0#
#405
b100 5
1#
#410
0#
#415
b101 5
1#
#420
0#
#425
b110 5
1#
#430
0#
#435
b111 5
1#
#440
0#
#445
06
b0 5
1#
#450
0#
#455
1!
1#
#460
0#
#465
1#
#470
0#
#475
1#
#480
0#
#484
b100 %
b100 -
b100 *
#485
b10 "
b10 /
b100 1
0!
16
b1000 3
1'
1#
#490
0#
#495
b1 "
b1 /
b10 1
b1 5
b100 3
1#
#500
0#
#505
b0 "
b0 /
b1 1
b10 5
b10 3
1#
0'
#510
0#
#515
b0 1
b11 5
b1 3
1#
#520
0#
#525
b100 5
b0 3
1#
#530
0#
#535
b101 5
1#
#540
0#
#545
b110 5
1#
#550
0#
#555
b111 5
1#
#560
0#
#565
06
b0 5
1#
#570
0#
#575
1!
1#
#580
0#
#585
1#
#590
0#
#595
1#
#600
0#
#605
b101 %
b101 -
1#
b101 *
#606
1'
#610
0#
#615
b10 "
b10 /
b101 1
0!
16
b1010 3
1#
#620
0#
#625
b1 "
b1 /
b10 1
b1 5
b101 3
1#
#626
0'
#630
0#
#635
b0 "
b0 /
b1 1
b10 5
b10 3
1#
#640
0#
#645
b0 1
b11 5
b1 3
1#
#650
0#
#655
b100 5
b0 3
1#
#660
0#
#665
b101 5
1#
#670
0#
#675
b110 5
1#
#680
0#
#685
b111 5
1#
#690
0#
#695
06
b0 5
1#
#700
0#
#705
1!
1#
#710
0#
#715
1#
#720
0#
#725
1#
#726
b110 %
b110 -
b110 *
#727
1'
#730
0#
#735
b11 "
b11 /
b110 1
0!
16
b1100 3
1#
#740
0#
#745
b1 "
b1 /
b11 1
b1 5
b110 3
1#
#747
0'
#750
0#
#755
b0 "
b0 /
b1 1
b10 5
b11 3
1#
#760
0#
#765
b0 1
b11 5
b1 3
1#
#770
0#
#775
b100 5
b0 3
1#
#780
0#
#785
b101 5
1#
#790
0#
#795
b110 5
1#
#800
0#
#805
b111 5
1#
#810
0#
#815
06
b0 5
1#
#820
0#
#825
1!
1#
#830
0#
#835
1#
#840
0#
#845
1#
#847
b111 %
b111 -
b111 *
#848
1'
#850
0#
#855
b11 "
b11 /
b111 1
0!
16
b1110 3
1#
#860
0#
#865
b1 "
b1 /
b11 1
b1 5
b111 3
1#
#868
0'
#870
0#
#875
b0 "
b0 /
b1 1
b10 5
b11 3
1#
#880
0#
#885
b0 1
b11 5
b1 3
1#
#890
0#
#895
b100 5
b0 3
1#
#900
0#
#905
b101 5
1#
#910
0#
#915
b110 5
1#
#920
0#
#925
b111 5
1#
#930
0#
#935
06
b0 5
1#
#940
0#
#945
1!
1#
#950
0#
#955
1#
#960
0#
#965
1#
#968
b1000 %
b1000 -
b1000 *
#969
1'
#970
0#
#975
b100 "
b100 /
b1000 1
0!
16
b10000 3
1#
#980
0#
#985
b10 "
b10 /
b100 1
b1 5
b1000 3
1#
#989
0'
#990
0#
#995
b1 "
b1 /
b10 1
b10 5
b100 3
1#
#1000
0#
#1005
b0 "
b0 /
b1 1
b11 5
b10 3
1#
#1010
0#
#1015
b0 1
b100 5
b1 3
1#
#1020
0#
#1025
b101 5
b0 3
1#
#1030
0#
#1035
b110 5
1#
#1040
0#
#1045
b111 5
1#
#1050
0#
#1055
06
b0 5
1#
#1060
0#
#1065
1!
1#
#1070
0#
#1075
1#
#1080
0#
#1085
1#
#1089
b1001 %
b1001 -
b1001 *
#1090
1'
0#
#1095
b100 "
b100 /
b1001 1
0!
16
b10010 3
1#
#1100
0#
#1105
b10 "
b10 /
b100 1
b1 5
b1001 3
1#
#1110
0#
0'
#1115
b1 "
b1 /
b10 1
b10 5
b100 3
1#
#1120
0#
#1125
b0 "
b0 /
b1 1
b11 5
b10 3
1#
#1130
0#
#1135
b0 1
b100 5
b1 3
1#
#1140
0#
#1145
b101 5
b0 3
1#
#1150
0#
#1155
b110 5
1#
#1160
0#
#1165
b111 5
1#
#1170
0#
#1175
06
b0 5
1#
#1180
0#
#1185
1!
1#
#1190
0#
#1195
1#
#1200
0#
#1205
1#
#1210
b1010 %
b1010 -
0#
b1010 *
#1211
1'
#1215
b101 "
b101 /
b1010 1
0!
16
b10100 3
1#
#1220
0#
#1225
b10 "
b10 /
b101 1
b1 5
b1010 3
1#
#1230
0#
#1231
0'
#1235
b1 "
b1 /
b10 1
b10 5
b101 3
1#
#1240
0#
#1245
b0 "
b0 /
b1 1
b11 5
b10 3
1#
#1250
0#
#1255
b0 1
b100 5
b1 3
1#
#1260
0#
#1265
b101 5
b0 3
1#
#1270
0#
#1275
b110 5
1#
#1280
0#
#1285
b111 5
1#
#1290
0#
#1295
06
b0 5
1#
#1300
0#
#1305
1!
1#
#1310
0#
#1315
1#
#1320
0#
#1325
1#
#1330
0#
#1331
b1011 %
b1011 -
b1011 *
#1332
1'
#1335
b101 "
b101 /
b1011 1
0!
16
b10110 3
1#
#1340
0#
#1345
b10 "
b10 /
b101 1
b1 5
b1011 3
1#
#1350
0#
#1352
0'
#1355
b1 "
b1 /
b10 1
b10 5
b101 3
1#
#1360
0#
#1365
b0 "
b0 /
b1 1
b11 5
b10 3
1#
#1370
0#
#1375
b0 1
b100 5
b1 3
1#
#1380
0#
#1385
b101 5
b0 3
1#
#1390
0#
#1395
b110 5
1#
#1400
0#
#1405
b111 5
1#
#1410
0#
#1415
06
b0 5
1#
#1420
0#
#1425
1!
1#
#1430
0#
#1435
1#
#1440
0#
#1445
1#
#1450
0#
#1452
b1100 %
b1100 -
b1100 *
#1453
1'
#1455
b110 "
b110 /
b1100 1
0!
16
b11000 3
1#
#1460
0#
#1465
b11 "
b11 /
b110 1
b1 5
b1100 3
1#
#1470
0#
#1473
0'
#1475
b1 "
b1 /
b11 1
b10 5
b110 3
1#
#1480
0#
#1485
b0 "
b0 /
b1 1
b11 5
b11 3
1#
#1490
0#
#1495
b0 1
b100 5
b1 3
1#
#1500
0#
#1505
b101 5
b0 3
1#
#1510
0#
#1515
b110 5
1#
#1520
0#
#1525
b111 5
1#
#1530
0#
#1535
06
b0 5
1#
#1540
0#
#1545
1!
1#
#1550
0#
#1555
1#
#1560
0#
#1565
1#
#1570
0#
#1573
b1101 %
b1101 -
b1101 *
#1574
1'
#1575
b110 "
b110 /
b1101 1
0!
16
b11010 3
1#
#1580
0#
#1585
b11 "
b11 /
b110 1
b1 5
b1101 3
1#
#1590
0#
#1594
0'
#1595
b1 "
b1 /
b11 1
b10 5
b110 3
1#
#1600
0#
#1605
b0 "
b0 /
b1 1
b11 5
b11 3
1#
#1610
0#
#1615
b0 1
b100 5
b1 3
1#
#1620
0#
#1625
b101 5
b0 3
1#
#1630
0#
#1635
b110 5
1#
#1640
0#
#1645
b111 5
1#
#1650
0#
#1655
06
b0 5
1#
#1660
0#
#1665
1!
1#
#1670
0#
#1675
1#
#1680
0#
#1685
1#
#1690
0#
#1694
b1110 %
b1110 -
b1110 *
#1695
b111 "
b111 /
b1110 1
0!
16
b11100 3
1'
1#
#1700
0#
#1705
b11 "
b11 /
b111 1
b1 5
b1110 3
1#
#1710
0#
#1715
b1 "
b1 /
b11 1
b10 5
b111 3
1#
0'
#1720
0#
#1725
b0 "
b0 /
b1 1
b11 5
b11 3
1#
#1730
0#
#1735
b0 1
b100 5
b1 3
1#
#1740
0#
#1745
b101 5
b0 3
1#
#1750
0#
#1755
b110 5
1#
#1760
0#
#1765
b111 5
1#
#1770
0#
#1775
06
b0 5
1#
#1780
0#
#1785
1!
1#
#1790
0#
#1795
1#
#1800
0#
#1805
1#
#1810
0#
#1815
b1111 %
b1111 -
1#
b1111 *
#1816
1'
#1820
0#
#1825
b111 "
b111 /
b1111 1
0!
16
b11110 3
1#
#1830
0#
#1835
b11 "
b11 /
b111 1
b1 5
b1111 3
1#
#1836
0'
#1840
0#
#1845
b1 "
b1 /
b11 1
b10 5
b111 3
1#
#1850
0#
#1855
b0 "
b0 /
b1 1
b11 5
b11 3
1#
#1860
0#
#1865
b0 1
b100 5
b1 3
1#
#1870
0#
#1875
b101 5
b0 3
1#
#1880
0#
#1885
b110 5
1#
#1890
0#
#1895
b111 5
1#
#1900
0#
#1905
06
b0 5
1#
#1910
0#
#1915
1!
1#
#1920
0#
#1925
1#
#1930
0#
#1935
1#
#1936
b10000 %
b10000 -
b10000 *
#1937
1'
#1940
0#
#1945
b1000 "
b1000 /
b10000 1
0!
16
b100000 3
1#
#1950
0#
#1955
b100 "
b100 /
b1000 1
b1 5
b10000 3
1#
#1957
0'
#1960
0#
#1965
b10 "
b10 /
b100 1
b10 5
b1000 3
1#
#1970
0#
#1975
b1 "
b1 /
b10 1
b11 5
b100 3
1#
#1980
0#
#1985
b0 "
b0 /
b1 1
b100 5
b10 3
1#
#1990
0#
#1995
b0 1
b101 5
b1 3
1#
#2000
0#
#2005
b110 5
b0 3
1#
#2010
0#
#2015
b111 5
1#
#2020
0#
#2025
06
b0 5
1#
#2030
0#
#2035
1!
1#
#2040
0#
#2045
1#
#2050
0#
#2055
1#
#2057
b10001 %
b10001 -
b10001 *
#2058
1'
#2060
0#
#2065
b1000 "
b1000 /
b10001 1
0!
16
b100010 3
1#
#2070
0#
#2075
b100 "
b100 /
b1000 1
b1 5
b10001 3
1#
#2078
0'
#2080
0#
#2085
b10 "
b10 /
b100 1
b10 5
b1000 3
1#
#2090
0#
#2095
b1 "
b1 /
b10 1
b11 5
b100 3
1#
#2100
0#
#2105
b0 "
b0 /
b1 1
b100 5
b10 3
1#
#2110
0#
#2115
b0 1
b101 5
b1 3
1#
#2120
0#
#2125
b110 5
b0 3
1#
#2130
0#
#2135
b111 5
1#
#2140
0#
#2145
06
b0 5
1#
#2150
0#
#2155
1!
1#
#2160
0#
#2165
1#
#2170
0#
#2175
1#
#2178
b10010 %
b10010 -
b10010 *
#2179
1'
#2180
0#
#2185
b1001 "
b1001 /
b10010 1
0!
16
b100100 3
1#
#2190
0#
#2195
b100 "
b100 /
b1001 1
b1 5
b10010 3
1#
#2199
0'
#2200
0#
#2205
b10 "
b10 /
b100 1
b10 5
b1001 3
1#
#2210
0#
#2215
b1 "
b1 /
b10 1
b11 5
b100 3
1#
#2220
0#
#2225
b0 "
b0 /
b1 1
b100 5
b10 3
1#
#2230
0#
#2235
b0 1
b101 5
b1 3
1#
#2240
0#
#2245
b110 5
b0 3
1#
#2250
0#
#2255
b111 5
1#
#2260
0#
#2265
06
b0 5
1#
#2270
0#
#2275
1!
1#
#2280
0#
#2285
1#
#2290
0#
#2295
1#
#2299
b10011 %
b10011 -
b10011 *
#2300
1'
0#
#2305
b1001 "
b1001 /
b10011 1
0!
16
b100110 3
1#
#2310
0#
#2315
b100 "
b100 /
b1001 1
b1 5
b10011 3
1#
#2320
0#
0'
#2325
b10 "
b10 /
b100 1
b10 5
b1001 3
1#
#2330
0#
#2335
b1 "
b1 /
b10 1
b11 5
b100 3
1#
#2340
0#
#2345
b0 "
b0 /
b1 1
b100 5
b10 3
1#
#2350
0#
#2355
b0 1
b101 5
b1 3
1#
#2360
0#
#2365
b110 5
b0 3
1#
#2370
0#
#2375
b111 5
1#
#2380
0#
#2385
06
b0 5
1#
#2390
0#
#2395
1!
1#
#2400
0#
#2405
1#
#2410
0#
#2415
1#
#2420
b10100 %
b10100 -
0#
b10100 *
#2421
1'
#2425
b1010 "
b1010 /
b10100 1
0!
16
b101000 3
1#
#2430
0#
#2435
b101 "
b101 /
b1010 1
b1 5
b10100 3
1#
#2440
0#
#2441
0'
#2445
b10 "
b10 /
b101 1
b10 5
b1010 3
1#
#2450
0#
#2455
b1 "
b1 /
b10 1
b11 5
b101 3
1#
#2460
0#
#2465
b0 "
b0 /
b1 1
b100 5
b10 3
1#
#2470
0#
#2475
b0 1
b101 5
b1 3
1#
#2480
0#
#2485
b110 5
b0 3
1#
#2490
0#
#2495
b111 5
1#
#2500
0#
#2505
06
b0 5
1#
#2510
0#
#2515
1!
1#
#2520
0#
#2525
1#
#2530
0#
#2535
1#
#2540
0#
#2541
b10101 %
b10101 -
b10101 *
#2542
1'
#2545
b1010 "
b1010 /
b10101 1
0!
16
b101010 3
1#
#2550
0#
#2555
b101 "
b101 /
b1010 1
b1 5
b10101 3
1#
#2560
0#
#2562
0'
#2565
b10 "
b10 /
b101 1
b10 5
b1010 3
1#
#2570
0#
#2575
b1 "
b1 /
b10 1
b11 5
b101 3
1#
#2580
0#
#2585
b0 "
b0 /
b1 1
b100 5
b10 3
1#
#2590
0#
#2595
b0 1
b101 5
b1 3
1#
#2600
0#
#2605
b110 5
b0 3
1#
#2610
0#
#2615
b111 5
1#
#2620
0#
#2625
06
b0 5
1#
#2630
0#
#2635
1!
1#
#2640
0#
#2645
1#
#2650
0#
#2655
1#
#2660
0#
#2662
b10110 %
b10110 -
b10110 *
#2663
1'
#2665
b1011 "
b1011 /
b10110 1
0!
16
b101100 3
1#
#2670
0#
#2675
b101 "
b101 /
b1011 1
b1 5
b10110 3
1#
#2680
0#
#2683
0'
#2685
b10 "
b10 /
b101 1
b10 5
b1011 3
1#
#2690
0#
#2695
b1 "
b1 /
b10 1
b11 5
b101 3
1#
#2700
0#
#2705
b0 "
b0 /
b1 1
b100 5
b10 3
1#
#2710
0#
#2715
b0 1
b101 5
b1 3
1#
#2720
0#
#2725
b110 5
b0 3
1#
#2730
0#
#2735
b111 5
1#
#2740
0#
#2745
06
b0 5
1#
#2750
0#
#2755
1!
1#
#2760
0#
#2765
1#
#2770
0#
#2775
1#
#2780
0#
#2783
b10111 %
b10111 -
b10111 *
#2784
1'
#2785
b1011 "
b1011 /
b10111 1
0!
16
b101110 3
1#
#2790
0#
#2795
b101 "
b101 /
b1011 1
b1 5
b10111 3
1#
#2800
0#
#2804
0'
#2805
b10 "
b10 /
b101 1
b10 5
b1011 3
1#
#2810
0#
#2815
b1 "
b1 /
b10 1
b11 5
b101 3
1#
#2820
0#
#2825
b0 "
b0 /
b1 1
b100 5
b10 3
1#
#2830
0#
#2835
b0 1
b101 5
b1 3
1#
#2840
0#
#2845
b110 5
b0 3
1#
#2850
0#
#2855
b111 5
1#
#2860
0#
#2865
06
b0 5
1#
#2870
0#
#2875
1!
1#
#2880
0#
#2885
1#
#2890
0#
#2895
1#
#2900
0#
#2904
b11000 %
b11000 -
b11000 *
#2905
b1100 "
b1100 /
b11000 1
0!
16
b110000 3
1'
1#
#2910
0#
#2915
b110 "
b110 /
b1100 1
b1 5
b11000 3
1#
#2920
0#
#2925
b11 "
b11 /
b110 1
b10 5
b1100 3
1#
0'
#2930
0#
#2935
b1 "
b1 /
b11 1
b11 5
b110 3
1#
#2940
0#
#2945
b0 "
b0 /
b1 1
b100 5
b11 3
1#
#2950
0#
#2955
b0 1
b101 5
b1 3
1#
#2960
0#
#2965
b110 5
b0 3
1#
#2970
0#
#2975
b111 5
1#
#2980
0#
#2985
06
b0 5
1#
#2990
0#
#2995
1!
1#
#3000
0#
#3005
1#
#3010
0#
#3015
1#
#3020
0#
#3025
b11001 %
b11001 -
1#
b11001 *
#3026
1'
#3030
0#
#3035
b1100 "
b1100 /
b11001 1
0!
16
b110010 3
1#
#3040
0#
#3045
b110 "
b110 /
b1100 1
b1 5
b11001 3
1#
#3046
0'
#3050
0#
#3055
b11 "
b11 /
b110 1
b10 5
b1100 3
1#
#3060
0#
#3065
b1 "
b1 /
b11 1
b11 5
b110 3
1#
#3070
0#
#3075
b0 "
b0 /
b1 1
b100 5
b11 3
1#
#3080
0#
#3085
b0 1
b101 5
b1 3
1#
#3090
0#
#3095
b110 5
b0 3
1#
#3100
0#
#3105
b111 5
1#
#3110
0#
#3115
06
b0 5
1#
#3120
0#
#3125
1!
1#
#3130
0#
#3135
1#
#3140
0#
#3145
1#
#3146
b11010 %
b11010 -
b11010 *
#3147
1'
#3150
0#
#3155
b1101 "
b1101 /
b11010 1
0!
16
b110100 3
1#
#3160
0#
#3165
b110 "
b110 /
b1101 1
b1 5
b11010 3
1#
#3167
0'
#3170
0#
#3175
b11 "
b11 /
b110 1
b10 5
b1101 3
1#
#3180
0#
#3185
b1 "
b1 /
b11 1
b11 5
b110 3
1#
#3190
0#
#3195
b0 "
b0 /
b1 1
b100 5
b11 3
1#
#3200
0#
#3205
b0 1
b101 5
b1 3
1#
#3210
0#
#3215
b110 5
b0 3
1#
#3220
0#
#3225
b111 5
1#
#3230
0#
#3235
06
b0 5
1#
#3240
0#
#3245
1!
1#
#3250
0#
#3255
1#
#3260
0#
#3265
1#
#3267
b11011 %
b11011 -
b11011 *
#3268
1'
#3270
0#
#3275
b1101 "
b1101 /
b11011 1
0!
16
b110110 3
1#
#3280
0#
#3285
b110 "
b110 /
b1101 1
b1 5
b11011 3
1#
#3288
0'
#3290
0#
#3295
b11 "
b11 /
b110 1
b10 5
b1101 3
1#
#3300
0#
#3305
b1 "
b1 /
b11 1
b11 5
b110 3
1#
#3310
0#
#3315
b0 "
b0 /
b1 1
b100 5
b11 3
1#
#3320
0#
#3325
b0 1
b101 5
b1 3
1#
#3330
0#
#3335
b110 5
b0 3
1#
#3340
0#
#3345
b111 5
1#
#3350
0#
#3355
06
b0 5
1#
#3360
0#
#3365
1!
1#
#3370
0#
#3375
1#
#3380
0#
#3385
1#
#3388
b11100 %
b11100 -
b11100 *
#3389
1'
#3390
0#
#3395
b1110 "
b1110 /
b11100 1
0!
16
b111000 3
1#
#3400
0#
#3405
b111 "
b111 /
b1110 1
b1 5
b11100 3
1#
#3409
0'
#3410
0#
#3415
b11 "
b11 /
b111 1
b10 5
b1110 3
1#
#3420
0#
#3425
b1 "
b1 /
b11 1
b11 5
b111 3
1#
#3430
0#
#3435
b0 "
b0 /
b1 1
b100 5
b11 3
1#
#3440
0#
#3445
b0 1
b101 5
b1 3
1#
#3450
0#
#3455
b110 5
b0 3
1#
#3460
0#
#3465
b111 5
1#
#3470
0#
#3475
06
b0 5
1#
#3480
0#
#3485
1!
1#
#3490
0#
#3495
1#
#3500
0#
#3505
1#
#3509
b11101 %
b11101 -
b11101 *
#3510
1'
0#
#3515
b1110 "
b1110 /
b11101 1
0!
16
b111010 3
1#
#3520
0#
#3525
b111 "
b111 /
b1110 1
b1 5
b11101 3
1#
#3530
0#
0'
#3535
b11 "
b11 /
b111 1
b10 5
b1110 3
1#
#3540
0#
#3545
b1 "
b1 /
b11 1
b11 5
b111 3
1#
#3550
0#
#3555
b0 "
b0 /
b1 1
b100 5
b11 3
1#
#3560
0#
#3565
b0 1
b101 5
b1 3
1#
#3570
0#
#3575
b110 5
b0 3
1#
#3580
0#
#3585
b111 5
1#
#3590
0#
#3595
06
b0 5
1#
#3600
0#
#3605
1!
1#
#3610
0#
#3615
1#
#3620
0#
#3625
1#
#3630
b11110 %
b11110 -
0#
b11110 *
#3631
1'
#3635
b1111 "
b1111 /
b11110 1
0!
16
b111100 3
1#
#3640
0#
#3645
b111 "
b111 /
b1111 1
b1 5
b11110 3
1#
#3650
0#
#3651
0'
#3655
b11 "
b11 /
b111 1
b10 5
b1111 3
1#
#3660
0#
#3665
b1 "
b1 /
b11 1
b11 5
b111 3
1#
#3670
0#
#3675
b0 "
b0 /
b1 1
b100 5
b11 3
1#
#3680
0#
#3685
b0 1
b101 5
b1 3
1#
#3690
0#
#3695
b110 5
b0 3
1#
#3700
0#
#3705
b111 5
1#
#3710
0#
#3715
06
b0 5
1#
#3720
0#
#3725
1!
1#
#3730
0#
#3735
1#
#3740
0#
#3745
1#
#3750
0#
#3751
b11111 %
b11111 -
b11111 *
#3752
1'
#3755
b1111 "
b1111 /
b11111 1
0!
16
b111110 3
1#
#3760
0#
#3765
b111 "
b111 /
b1111 1
b1 5
b11111 3
1#
#3770
0#
#3772
0'
#3775
b11 "
b11 /
b111 1
b10 5
b1111 3
1#
#3780
0#
#3785
b1 "
b1 /
b11 1
b11 5
b111 3
1#
#3790
0#
#3795
b0 "
b0 /
b1 1
b100 5
b11 3
1#
#3800
0#
#3805
b0 1
b101 5
b1 3
1#
#3810
0#
#3815
b110 5
b0 3
1#
#3820
0#
#3825
b111 5
1#
#3830
0#
#3835
06
b0 5
1#
#3840
0#
#3845
1!
1#
#3850
0#
#3855
1#
#3860
0#
#3865
1#
#3870
0#
#3872
b100000 %
b100000 -
b100000 *
#3873
1'
#3875
b10000 "
b10000 /
b100000 1
0!
16
b1000000 3
1#
#3880
0#
#3885
b1000 "
b1000 /
b10000 1
b1 5
b100000 3
1#
#3890
0#
#3893
0'
#3895
b100 "
b100 /
b1000 1
b10 5
b10000 3
1#
#3900
0#
#3905
b10 "
b10 /
b100 1
b11 5
b1000 3
1#
#3910
0#
#3915
b1 "
b1 /
b10 1
b100 5
b100 3
1#
#3920
0#
#3925
b0 "
b0 /
b1 1
b101 5
b10 3
1#
#3930
0#
#3935
b0 1
b110 5
b1 3
1#
#3940
0#
#3945
b111 5
b0 3
1#
#3950
0#
#3955
06
b0 5
1#
#3960
0#
#3965
1!
1#
#3970
0#
#3975
1#
#3980
0#
#3985
1#
#3990
0#
#3993
b100001 %
b100001 -
b100001 *
#3994
1'
#3995
b10000 "
b10000 /
b100001 1
0!
16
b1000010 3
1#
#4000
0#
#4005
b1000 "
b1000 /
b10000 1
b1 5
b100001 3
1#
#4010
0#
#4014
0'
#4015
b100 "
b100 /
b1000 1
b10 5
b10000 3
1#
#4020
0#
#4025
b10 "
b10 /
b100 1
b11 5
b1000 3
1#
#4030
0#
#4035
b1 "
b1 /
b10 1
b100 5
b100 3
1#
#4040
0#
#4045
b0 "
b0 /
b1 1
b101 5
b10 3
1#
#4050
0#
#4055
b0 1
b110 5
b1 3
1#
#4060
0#
#4065
b111 5
b0 3
1#
#4070
0#
#4075
06
b0 5
1#
#4080
0#
#4085
1!
1#
#4090
0#
#4095
1#
#4100
0#
#4105
1#
#4110
0#
#4114
b100010 %
b100010 -
b100010 *
#4115
b10001 "
b10001 /
b100010 1
0!
16
b1000100 3
1'
1#
#4120
0#
#4125
b1000 "
b1000 /
b10001 1
b1 5
b100010 3
1#
#4130
0#
#4135
b100 "
b100 /
b1000 1
b10 5
b10001 3
1#
0'
#4140
0#
#4145
b10 "
b10 /
b100 1
b11 5
b1000 3
1#
#4150
0#
#4155
b1 "
b1 /
b10 1
b100 5
b100 3
1#
#4160
0#
#4165
b0 "
b0 /
b1 1
b101 5
b10 3
1#
#4170
0#
#4175
b0 1
b110 5
b1 3
1#
#4180
0#
#4185
b111 5
b0 3
1#
#4190
0#
#4195
06
b0 5
1#
#4200
0#
#4205
1!
1#
#4210
0#
#4215
1#
#4220
0#
#4225
1#
#4230
0#
#4235
b100011 %
b100011 -
1#
b100011 *
#4236
1'
#4240
0#
#4245
b10001 "
b10001 /
b100011 1
0!
16
b1000110 3
1#
#4250
0#
#4255
b1000 "
b1000 /
b10001 1
b1 5
b100011 3
1#
#4256
0'
#4260
0#
#4265
b100 "
b100 /
b1000 1
b10 5
b10001 3
1#
#4270
0#
#4275
b10 "
b10 /
b100 1
b11 5
b1000 3
1#
#4280
0#
#4285
b1 "
b1 /
b10 1
b100 5
b100 3
1#
#4290
0#
#4295
b0 "
b0 /
b1 1
b101 5
b10 3
1#
#4300
0#
#4305
b0 1
b110 5
b1 3
1#
#4310
0#
#4315
b111 5
b0 3
1#
#4320
0#
#4325
06
b0 5
1#
#4330
0#
#4335
1!
1#
#4340
0#
#4345
1#
#4350
0#
#4355
1#
#4356
b100100 %
b100100 -
b100100 *
#4357
1'
#4360
0#
#4365
b10010 "
b10010 /
b100100 1
0!
16
b1001000 3
1#
#4370
0#
#4375
b1001 "
b1001 /
b10010 1
b1 5
b100100 3
1#
#4377
0'
#4380
0#
#4385
b100 "
b100 /
b1001 1
b10 5
b10010 3
1#
#4390
0#
#4395
b10 "
b10 /
b100 1
b11 5
b1001 3
1#
#4400
0#
#4405
b1 "
b1 /
b10 1
b100 5
b100 3
1#
#4410
0#
#4415
b0 "
b0 /
b1 1
b101 5
b10 3
1#
#4420
0#
#4425
b0 1
b110 5
b1 3
1#
#4430
0#
#4435
b111 5
b0 3
1#
